{
    "sensory_title_security": "Sensory Güvenliği",
    "sensory_button_contact": "Desteğe Ulaşın",
    "sensory_button_vote": "Sensory'ye Oy Verin",
    "integrity_verification": "Bütünlüğün Doğrulanıyor",
    "integrity_solve_captcha": "Robot olup olmadığınıza bakıyoruz. Topluluğa ulaşmak için lütfen captcha'yi çözün.",
    "integrity_status_failed": "Doğrulama Başarısız",
    "integrity_status_complete": "Doğrulama Başarılı",
    "integrity_expires": "Doğrulamanın süresi şu zamanda dolacak",
    "integrity_expires_minutes": "Dakikalar",
    "integrity_expires_seconds": "Saniyeler",
    "integrity_something_happened": "Sensory hizmetlerine bağlanırken bir hata oluştu. Hata devam ederse bize ulaşın.",
    "integrity_api_error_code": "hata kodu:"
}